dexapi
