Metadata-Version: 2.1
Name: dexapi
Version: 0.1.1
Summary: Python wraper for bitquery.io DEX API
Home-page: https://github.com/kayrauygun/dexapi
Author: Kayra Uygun
Author-email: kayrauygun@gmail.com
License: UNKNOWN
Platform: UNKNOWN
Classifier: Programming Language :: Python :: 3
Classifier: License :: OSI Approved :: MIT License
Classifier: Operating System :: OS Independent
Requires-Python: >=3.6
